pycule/__init__.py
pycule/callbacks.py
pycule/core.py
pycule/decorators.py
pycule/urls.py
PyCule-0.1.3b0.dist-info/METADATA
PyCule-0.1.3b0.dist-info/WHEEL
PyCule-0.1.3b0.dist-info/top_level.txt
PyCule-0.1.3b0.dist-info/RECORD
