Metadata-Version: 2.1
Name: PyCule
Version: 0.1.3b0
Summary: Python wrapper for the MCule Ultimate API
Home-page: https://github.com/Waztom/pycule
Author: Warren Thompson
Author-email: waztom@gmail.com
License: MIT
Platform: UNKNOWN
Classifier: Intended Audience :: Developers
Classifier: Intended Audience :: Science/Research
Classifier: License :: OSI Approved :: MIT License
Classifier: Programming Language :: Python :: 3.7
Classifier: Topic :: Software Development :: Libraries :: Python Modules
Requires-Dist: requests (==2.23.0)
